README.md
setup.py
firi/__init__.py
firi/client.py
firi/endpoints.py
firi/markets.py
firi/utils.py
firi.egg-info/PKG-INFO
firi.egg-info/SOURCES.txt
firi.egg-info/dependency_links.txt
firi.egg-info/top_level.txt