Metadata-Version: 2.1
Name: firi
Version: 0.0.1
Summary: UNKNOWN
Home-page: https://github.com/offish/firi
Author: offish
Author-email: overutilization@gmail.com
License: MIT
Download-URL: https://github.com/offish/firi/tarball/v0.0.1
Platform: UNKNOWN
Classifier: Programming Language :: Python :: 3
Classifier: License :: OSI Approved :: MIT License
Classifier: Operating System :: OS Independent
Requires-Python: >=3.6
